easy_tensorflow_models/__init__.py
easy_tensorflow_models-0.2.3.dist-info/LICENSE
easy_tensorflow_models-0.2.3.dist-info/METADATA
easy_tensorflow_models-0.2.3.dist-info/WHEEL
easy_tensorflow_models-0.2.3.dist-info/top_level.txt
easy_tensorflow_models-0.2.3.dist-info/RECORD
